distributions/Binomialdistribution.py
distributions/Gaussiandistribution.py
distributions/Generaldistribution.py
distributions/__init__.py
gauss_distribs-0.1.dist-info/METADATA
gauss_distribs-0.1.dist-info/WHEEL
gauss_distribs-0.1.dist-info/top_level.txt
gauss_distribs-0.1.dist-info/RECORD
